benchmarks/__init__.py
benchmarks/benchmark.py
benchmarks/data.py
benchmarks/models.py
benchmarks/profiler.py
benchmarks/run_historical_benchmarks.py
benchmarks/dash_app/__init__.py
benchmarks/dash_app/app.py
benchmarks/dash_app/load_data.py
configs/__init__.py
configs/default.yaml
crypten/__init__.py
crypten/autograd_cryptensor.py
crypten/cryptensor.py
crypten/encoder.py
crypten/gradients.py
crypten/common/__init__.py
crypten/common/rng.py
crypten/common/serial.py
crypten/common/tensor_types.py
crypten/common/util.py
crypten/common/functions/__init__.py
crypten/common/functions/approximations.py
crypten/common/functions/dropout.py
crypten/common/functions/logic.py
crypten/common/functions/maximum.py
crypten/common/functions/pooling.py
crypten/common/functions/power.py
crypten/common/functions/regular.py
crypten/common/functions/sampling.py
crypten/communicator/__init__.py
crypten/communicator/communicator.py
crypten/communicator/distributed_communicator.py
crypten/communicator/in_process_communicator.py
crypten/config/__init__.py
crypten/config/config.py
crypten/cuda/__init__.py
crypten/cuda/cuda_tensor.py
crypten/debug/__init__.py
crypten/debug/debug.py
crypten/models/__init__.py
crypten/mpc/__init__.py
crypten/mpc/context.py
crypten/mpc/mpc.py
crypten/mpc/ptype.py
crypten/mpc/primitives/__init__.py
crypten/mpc/primitives/arithmetic.py
crypten/mpc/primitives/beaver.py
crypten/mpc/primitives/binary.py
crypten/mpc/primitives/circuit.py
crypten/mpc/primitives/converters.py
crypten/mpc/primitives/replicated.py
crypten/mpc/provider/__init__.py
crypten/mpc/provider/homomorphic_provider.py
crypten/mpc/provider/tfp_provider.py
crypten/mpc/provider/ttp_provider.py
crypten/nn/__init__.py
crypten/nn/distances.py
crypten/nn/init.py
crypten/nn/loss.py
crypten/nn/module.py
crypten/nn/onnx_converter.py
crypten/nn/tensorboard.py
crypten/optim/__init__.py
crypten/optim/optimizer.py
crypten/optim/sgd.py
examples/__init__.py
examples/meters.py
examples/multiprocess_launcher.py
crypten-0.4.0.dist-info/LICENSE
crypten-0.4.0.dist-info/METADATA
crypten-0.4.0.dist-info/WHEEL
crypten-0.4.0.dist-info/top_level.txt
crypten-0.4.0.dist-info/RECORD
