Metadata-Version: 2.1
Name: crypten
Version: 0.4.0
Summary: CrypTen: secure machine learning in PyTorch.
Home-page: https://github.com/facebookresearch/CrypTen
Author: Facebook AI Research
License: MIT licensed, as found in the LICENSE file
Platform: UNKNOWN
License-File: LICENSE
